LICENSE
MANIFEST.in
README.md
setup.py
r3frame/__init__.py
r3frame/globs.py
r3frame/util.py
r3frame/version.py
r3frame/app/__init__.py
r3frame/app/event.py
r3frame/app/input.py
r3frame/app/proc.py
r3frame/app/rsrc.py
r3frame/app/ui/__init__.py
r3frame/app/ui/base.py
r3frame/app/ui/button.py
r3frame/app/ui/tooltip.py
r3frame/assets/fonts/megamax.ttf
r3frame/assets/images/burber.png
r3frame/assets/images/green-link.png
r3frame/assets/images/idle.png
r3frame/assets/images/link.png
r3frame/assets/images/r3-logo.ico
r3frame/assets/images/run.png
r3frame/game/__init__.py
r3frame/game/obj.py
r3frame/game/partition.py
r3frame_dev.egg-info/PKG-INFO
r3frame_dev.egg-info/SOURCES.txt
r3frame_dev.egg-info/dependency_links.txt
r3frame_dev.egg-info/requires.txt
r3frame_dev.egg-info/top_level.txt